{
  "paragraph": [
    {
      "paragraph_txt": "제가 가장 좋아하는 과목은 미술과 과학입니다. #@문장구분#미술은 다른 과목에 비해 배우는 것이 어렵지 않고 배울 때마다 새로운 것을 그리고 만드는 것이 재미있기 때문입니다. #@문장구분#또한 그림 그리는 것이나 만들기를 좋아하고 그림을 잘 그리는 편이라 미술에 대한 거부감 없이 미술이라는 과목을 더 좋아하는 것 같습니다.\n #@문장구분#과학은 배울 때마다 집에서는 해보기 어려운 여러 가지 실험을 하는데 저는 친구들과 실험을 하며 새로운 지식을 배우는 것이 좋습니다.\n #@문장구분#이상으로 제가 미술과 과학을 좋아하는 이유를 설명해보았습니다. #@문장구분#이러한 이유들로 인해 제가 가장 좋아하는 과목은 미술과 과학입니다.",
      "paragraph_len": 416,
      "paragraph_id": "001"
    }
  ],
  "score": {
    "paragraph_score": [
      {
        "paragraph_scoreT": [
          3,
          3,
          3
        ],
        "paragraph_scoreT_detail": {
          "paragraph_scoreT_exp": [
            [
              3,
              3,
              0
            ],
            [
              3,
              3,
              0
            ],
            [
              3,
              3,
              0
            ]
          ]
        },
        "paragraph_scoreT_avg": 3,
        "paragraph_id": "001"
      }
    ],
    "essay_scoreT": [
      25.666666,
      28.066666,
      30
    ],
    "essay_scoreT_avg": 27.91111,
    "essay_scoreT_detail": {
      "essay_scoreT_org": [
        [
          3,
          0,
          0,
          2
        ],
        [
          3,
          0,
          0,
          2
        ],
        [
          3,
          0,
          0,
          3
        ]
      ],
      "essay_scoreT_cont": [
        [
          2,
          2,
          0,
          2
        ],
        [
          3,
          2,
          0,
          3
        ],
        [
          3,
          3,
          0,
          3
        ]
      ],
      "essay_scoreT_exp": [
        [
          3,
          3,
          0
        ],
        [
          3,
          3,
          0
        ],
        [
          3,
          3,
          0
        ]
      ]
    }
  },
  "student": {
    "date": "2021.10.15",
    "student_educated": true,
    "student_grade": "초등_5학년",
    "location": "042",
    "student_grade_group": "초등",
    "student_reading": 2
  },
  "rubric": {
    "essay_grade": "초등_5학년",
    "organization_weight": {
      "org_paragraph": 0,
      "org": 2,
      "org_essay": 5,
      "org_coherence": 0,
      "org_quantity": 1
    },
    "essay_type": "설명글",
    "content_weight": {
      "con_clearance": 4,
      "con_novelty": 4,
      "con": 4,
      "con_prompt": 0,
      "con_description": 2
    },
    "essay_main_subject": "가장 좋아하는 과목",
    "expression_weight": {
      "exp_style": 0,
      "exp_grammar": 4,
      "exp_vocab": 3,
      "exp": 4
    }
  },
  "correction": [],
  "info": {
    "essay_id": "ESSAY_40505",
    "essay_prompt": " 학교에서 많은 과목을 배우고 있습니다. 수학, 과학, 체육, 미술, 음악 정말 과목이 다양하죠! \n\n 하지만 다들 성격이 다르고 좋아하는 것도 달라서 제일 잘하고 재밌는 과목 또한 서로 다를 것으로 생각합니다.\n\n 여러분은 어떤 과목이 제일 재미있나요? 가장 좋아하는 과목과 그 이유를 작성해주세요.",
    "essay_type": "설명글",
    "essay_level": "3",
    "essay_len": 316,
    "essay_main_subject": "가장 좋아하는 과목"
  }
}