{
  "paragraph": [
    {
      "paragraph_txt": "제가 살고싶은 집은 넓은집입니다.#@문장구분# 1층은 온실이 있고,고양이도있습니다.#@문장구분# 온실은 여러가지 나무들과 물웅덩이, 여러가지의 꽃들이 있습니다.#@문장구분# 고양이는하얀색입니다.#@문장구분#\n2층은 넓은부얶이랑, 욕실이 있습니다.#@문장구분# 부얶은 요리할수있는 공간이 2곳이 있고, 큰 식탁이 3대가 있습니다.#@문장구분#\n욕실은 문을열면 적당한 크기의 욕실이 나옵니다.#@문장구분# 안에는 변기와 세면대, 욕조2대가 있습니다.#@문장구분#\n3층은 다락방이있고, 다락방 안에는 책장, 그리고 큰침대 2대가 있습니다.#@문장구분#\n책장엔 50가지가 넘는 책들이있고, 침대는 하얀 침대 입니다.#@문장구분#\n집 지붕은 검정색이며, 집 몸통은 하얀색 입니다.#@문장구분#\n마당엔 수영장이 있습니다.#@문장구분#\n그리고 그 옆엔 작은 테이블이 있습니다.#@문장구분#\n전 그런 집에서 살고싶습니다.#@문장구분#",
      "paragraph_len": 640,
      "paragraph_id": "001"
    }
  ],
  "score": {
    "paragraph_score": [
      {
        "paragraph_scoreT": [
          2,
          2.5714285,
          1.5714285
        ],
        "paragraph_scoreT_detail": {
          "paragraph_scoreT_exp": [
            [
              2,
              2,
              0
            ],
            [
              3,
              2,
              0
            ],
            [
              2,
              1,
              0
            ]
          ]
        },
        "paragraph_scoreT_avg": 2.0476189,
        "paragraph_id": "001"
      }
    ],
    "essay_scoreT": [
      24,
      23.419048,
      15.419047
    ],
    "essay_scoreT_avg": 20.946032,
    "essay_scoreT_detail": {
      "essay_scoreT_org": [
        [
          2,
          0,
          0,
          2
        ],
        [
          2,
          0,
          0,
          3
        ],
        [
          2,
          0,
          0,
          3
        ]
      ],
      "essay_scoreT_cont": [
        [
          3,
          3,
          0,
          3
        ],
        [
          2,
          2,
          0,
          3
        ],
        [
          1,
          1,
          0,
          2
        ]
      ],
      "essay_scoreT_exp": [
        [
          2,
          2,
          0
        ],
        [
          3,
          2,
          0
        ],
        [
          2,
          1,
          0
        ]
      ]
    }
  },
  "student": {
    "date": "2021.10.26",
    "student_educated": true,
    "student_grade": "초등_4학년",
    "location": "042",
    "student_grade_group": "초등",
    "student_reading": 2
  },
  "rubric": {
    "essay_grade": "초등_4학년",
    "organization_weight": {
      "org_paragraph": 0,
      "org": 2,
      "org_essay": 5,
      "org_coherence": 0,
      "org_quantity": 1
    },
    "essay_type": "설명글",
    "content_weight": {
      "con_clearance": 4,
      "con_novelty": 4,
      "con": 4,
      "con_prompt": 0,
      "con_description": 2
    },
    "essay_main_subject": "살고 싶은 집",
    "expression_weight": {
      "exp_style": 0,
      "exp_grammar": 4,
      "exp_vocab": 3,
      "exp": 4
    }
  },
  "correction": [
    {
      "sentence_corr_txt_grammar": "제가 살고 싶은 집은 넓은 집입니다.",
      "sentence_corr_reason": [
        ""
      ],
      "sentence_id": "0001",
      "sentence_corr_type": [
        "문법"
      ],
      "sentence_corr_detail_type": [
        "맞춤법"
      ],
      "sentence_txt": "제가 <문법_맞춤법>살고싶은 집은 넓은집입니다.</문법_맞춤법>",
      "sentence_corr_txt_styling": "",
      "paragraph_id": "001"
    },
    {
      "sentence_corr_txt_grammar": " 1층은 온실이 있고, 고양이도 있습니다.",
      "sentence_corr_reason": [
        ""
      ],
      "sentence_id": "0002",
      "sentence_corr_type": [
        "문법"
      ],
      "sentence_corr_detail_type": [
        "맞춤법"
      ],
      "sentence_txt": " 1층은 온실이 <문법_맞춤법>있고,고양이도있습니다.</문법_맞춤법>",
      "sentence_corr_txt_styling": "",
      "paragraph_id": "001"
    },
    {
      "sentence_corr_txt_grammar": " 온실은 여러 가지 나무들과 물웅덩이, 여러 가지의 꽃들이 있습니다.",
      "sentence_corr_reason": [
        ""
      ],
      "sentence_id": "0003",
      "sentence_corr_type": [
        "문법"
      ],
      "sentence_corr_detail_type": [
        "맞춤법"
      ],
      "sentence_txt": " 온실은 <문법_맞춤법>여러가지 나무들과 물웅덩이, 여러가지의</문법_맞춤법> 꽃들이 있습니다.",
      "sentence_corr_txt_styling": "",
      "paragraph_id": "001"
    },
    {
      "sentence_corr_txt_grammar": " 고양이는 하얀색입니다.",
      "sentence_corr_reason": [
        ""
      ],
      "sentence_id": "0004",
      "sentence_corr_type": [
        "문법"
      ],
      "sentence_corr_detail_type": [
        "맞춤법"
      ],
      "sentence_txt": " <문법_맞춤법>고양이는하얀색입니다.</문법_맞춤법>",
      "sentence_corr_txt_styling": "",
      "paragraph_id": "001"
    },
    {
      "sentence_corr_txt_grammar": "\n2층은 넓은 부엌이랑, 욕실이 있습니다.",
      "sentence_corr_reason": [
        ""
      ],
      "sentence_id": "0005",
      "sentence_corr_type": [
        "문법"
      ],
      "sentence_corr_detail_type": [
        "맞춤법"
      ],
      "sentence_txt": "\n2층은 <문법_맞춤법>넓은부얶이랑,</문법_맞춤법> 욕실이 있습니다.",
      "sentence_corr_txt_styling": "",
      "paragraph_id": "001"
    },
    {
      "sentence_corr_txt_grammar": " 부엌은 요리 할 수 있는 공간이 2곳이 있고, 큰 식탁이 3대가 있습니다.",
      "sentence_corr_reason": [
        ""
      ],
      "sentence_id": "0006",
      "sentence_corr_type": [
        "문법"
      ],
      "sentence_corr_detail_type": [
        "맞춤법"
      ],
      "sentence_txt": " <문법_맞춤법>부얶은 요리할수있는</문법_맞춤법> 공간이 2곳이 있고, 큰 식탁이 3대가 있습니다.",
      "sentence_corr_txt_styling": "",
      "paragraph_id": "001"
    },
    {
      "sentence_corr_txt_grammar": "\n욕실은 문을 열면 적당한 크기의 욕실이 나옵니다.",
      "sentence_corr_reason": [
        ""
      ],
      "sentence_id": "0007",
      "sentence_corr_type": [
        "문법"
      ],
      "sentence_corr_detail_type": [
        "맞춤법"
      ],
      "sentence_txt": "\n욕실은 <문법_맞춤법>문을열면</문법_맞춤법> 적당한 크기의 욕실이 나옵니다.",
      "sentence_corr_txt_styling": "",
      "paragraph_id": "001"
    },
    {
      "sentence_corr_txt_grammar": " 안에는 변기와 세면대, 욕조 2대가 있습니다.",
      "sentence_corr_reason": [
        ""
      ],
      "sentence_id": "0008",
      "sentence_corr_type": [
        "문법"
      ],
      "sentence_corr_detail_type": [
        "맞춤법"
      ],
      "sentence_txt": " 안에는 변기와 세면대, <문법_맞춤법>욕조2대가 있습니다.</문법_맞춤법>",
      "sentence_corr_txt_styling": "",
      "paragraph_id": "001"
    },
    {
      "sentence_corr_txt_grammar": "\n3층은 다락방이 있고, 다락방 안에는 책장, 그리고 큰 침대 2대가 있습니다.",
      "sentence_corr_reason": [
        ""
      ],
      "sentence_id": "0009",
      "sentence_corr_type": [
        "문법"
      ],
      "sentence_corr_detail_type": [
        "맞춤법"
      ],
      "sentence_txt": "\n3층은 <문법_맞춤법>다락방이있고, 다락방 안에는 책장, 그리고 큰침대 2대가 있습니다.</문법_맞춤법>",
      "sentence_corr_txt_styling": "",
      "paragraph_id": "001"
    },
    {
      "sentence_corr_txt_grammar": "\n책장엔 50가지가 넘는 책들이 있고, 침대는 하얀 침대입니다.",
      "sentence_corr_reason": [
        ""
      ],
      "sentence_id": "0010",
      "sentence_corr_type": [
        "문법"
      ],
      "sentence_corr_detail_type": [
        "맞춤법"
      ],
      "sentence_txt": "\n책장엔 50가지가 넘는 <문법_맞춤법>책들이있고, 침대는 하얀 침대 입니다</문법_맞춤법>.",
      "sentence_corr_txt_styling": "",
      "paragraph_id": "001"
    },
    {
      "sentence_corr_txt_grammar": "\n집 지붕은 검은색이며, 집 몸통은 하얀색입니다.",
      "sentence_corr_reason": [
        ""
      ],
      "sentence_id": "0011",
      "sentence_corr_type": [
        "문법"
      ],
      "sentence_corr_detail_type": [
        "맞춤법"
      ],
      "sentence_txt": "\n집 지붕은 <문법_맞춤법>검정색이며, 집 몸통은 하얀색 입니다.</문법_맞춤법>",
      "sentence_corr_txt_styling": "",
      "paragraph_id": "001"
    },
    {
      "sentence_corr_txt_grammar": "\n전 그런 집에서 살고 싶습니다.",
      "sentence_corr_reason": [
        ""
      ],
      "sentence_id": "0014",
      "sentence_corr_type": [
        "문법"
      ],
      "sentence_corr_detail_type": [
        "맞춤법"
      ],
      "sentence_txt": "\n전 그런 집에서 <문법_맞춤법>살고싶습니다.</문법_맞춤법>",
      "sentence_corr_txt_styling": "",
      "paragraph_id": "001"
    }
  ],
  "info": {
    "essay_id": "ESSAY_46135",
    "essay_prompt": " 우리가 사는 집은 모양과 구조가 다양합니다. 방이 여러 개인 집, 거실이 큰집, 화장실이 많은 집, 주방이 화려한 집, 전등이 많이 달린 집, 깔끔한 하얀 집 같이 여러 모양이 있어요.\n\n 그리고 방마다 특징이 있을 것 같아요. 놀이방, 게임방, 잠을 자는 방, 책을 읽는 방 등등 집의 모양과 방의 쓰임새가 다양합니다.\n\n 혹시, 여러분은 미래에 자신이 살고 싶은 집을 상상해 본 적이 있나요? 내가 살고 싶은 집을 먼저 설명해보고 그 집의 특징과 구조를 자세히 설명해보세요.\n\n방은 몇 개고 색깔은 어떨 것 같고 집의 생김새는 어떠할지 마음껏 표현해주세요!",
    "essay_type": "설명글",
    "essay_level": "3",
    "essay_len": 360,
    "essay_main_subject": "살고 싶은 집"
  }
}