{
  "paragraph": [
    {
      "paragraph_txt": "최근들어서 인터넷상에서도 그러고 주변 친구들도 티비에서도  리스펙이란 단어가 심심치 않게 나오고 있다.#@문장구분# 존경한다는 의미인데 정말 존경해서 그러는걸까 패드립과 마찬가지도 요즘 친구들 입에선 주저없이 나오는 말이다#@문장구분# 리스팩 하지만 많이 사용은 하지만 단어를 쓰는 일명 연예인들이나 사람들을 보면 의심의 눈초리가 생기는 것은 왜일까.#@문장구분# 예전 책에서 이세상에 존재하는 모든 것은 존중받아 마땅하다는 말이 생각난다. #@문장구분#그렇다.#@문장구분# 이 세상에 태어난 이상 우리는 누구나 다 존중받아야 한다.#@문장구분# 내가 존중받고 싶은만큼 타인도 존중하는 삶이 정말 좋은 삶이라고 생각된다.#@문장구분# 나는 평범한 가정에서 태어나 평범하게 자라서인지 아직까지는 누군가에게 무시당하거나 배려받지 못하다고 생각든적은 없지만 내가 그렇다고 모든 우리 사회 사람들이 다 존중받고 산다고 생각들지는 않는다.#@문장구분# 내가 어디서 어떡게 나에 대한 평판이 나올지 모를일입니다.#@문장구분#내 기분만 생각하지말고 항상 반대입장에서도 생각하고 배려해가며 살아야겠습니다.#@문장구분# 이러한 사례를 조사하면서 저는 남을 무시하게 되면 언젠간 그 죄의 무게는 자신에게 돌아 올것이라고 알게 되었고 앞으로 더욱더 남을 배려하고 존경하면서 살아야 할거입니다. #@문장구분#그러니까 내가 행동을 할떄도 내가 이렇게 나쁘게 행동하면 언젠가는 나에게 돌아오는구나 라는 생각을 하면서 그 행동을 받고 내가 기분이나쁠 것을 생각하면 딴사람 도 그행동을 받으면 기분이 나쁠것이기 떄문에 하면 안되겠다고 생각한다.#@문장구분#",
      "paragraph_len": 955,
      "paragraph_id": "001"
    }
  ],
  "score": {
    "paragraph_score": [
      {
        "paragraph_scoreT": [
          2.7142856,
          2.7142856,
          2.2857144
        ],
        "paragraph_scoreT_detail": {
          "paragraph_scoreT_exp": [
            [
              3,
              3,
              2
            ],
            [
              2,
              3,
              3
            ],
            [
              3,
              2,
              2
            ]
          ]
        },
        "paragraph_scoreT_avg": 2.5714285,
        "paragraph_id": "001"
      }
    ],
    "essay_scoreT": [
      23.079365,
      26.190475,
      25.97619
    ],
    "essay_scoreT_avg": 25.08201,
    "essay_scoreT_detail": {
      "essay_scoreT_org": [
        [
          2,
          2,
          2,
          3
        ],
        [
          2,
          3,
          3,
          3
        ],
        [
          2,
          3,
          3,
          3
        ]
      ],
      "essay_scoreT_cont": [
        [
          2,
          2,
          0,
          2
        ],
        [
          3,
          2,
          0,
          2
        ],
        [
          3,
          3,
          0,
          2
        ]
      ],
      "essay_scoreT_exp": [
        [
          3,
          3,
          2
        ],
        [
          2,
          3,
          3
        ],
        [
          3,
          2,
          2
        ]
      ]
    }
  },
  "student": {
    "date": "2021.12.23",
    "student_educated": true,
    "student_grade": "고등_2학년",
    "location": "063",
    "student_grade_group": "고등",
    "student_reading": 3
  },
  "rubric": {
    "essay_grade": "고등_2학년",
    "organization_weight": {
      "org_paragraph": 3,
      "org": 2,
      "org_essay": 3,
      "org_coherence": 2,
      "org_quantity": 1
    },
    "essay_type": "설명글",
    "content_weight": {
      "con_clearance": 4,
      "con_novelty": 3,
      "con": 4,
      "con_prompt": 0,
      "con_description": 1
    },
    "essay_main_subject": "타인을 중시하지 않았던 사례",
    "expression_weight": {
      "exp_style": 2,
      "exp_grammar": 2,
      "exp_vocab": 3,
      "exp": 4
    }
  },
  "correction": [],
  "info": {
    "essay_id": "ESSAY_77509",
    "essay_prompt": " 요즘 respect라는 단어가 감탄사처럼 사용됩니다. 존경한다는 표현을 표준국어대사전에서 살펴보면 높이어 귀중하게 대한다는 의미를 가집니다.\n\n 평소에도 우리는 타인에게 존경/존중받기를 원하며 사회적으로 인정받기 위해 각자만의 방식으로 자기 자신을 표현하고 노력합니다.\n\n 반대로 우리는 누군가에게 존중받지 못한 상황에 놓이면 자신이 타자에 의해 무시, 경시되고 있다는 인식으로 이어져 불편한 감정을 표출합니다.\n\n 여러분도 살아가면서 본인이 무시당하였다고 생각되었던 상황이 있을 것입니다. 또한, 상대방을 무시했던 상황도 있을 겁니다.\n\n 친구들과 장난을 하다가 자신도 모르게 친구의 기분을 나쁘게 했을 수도 있고 어른들에게 무시당해서 상처를 받았던 경험이 있을 것 같아요.\n\n 자신이나 타인이 누군가가 중시하는 것을 무시하고 배려하지 않았던 사례를 들고 그것이 어떤 결과를 가져왔는지 작성해주세요.\n\n 만약 그러한 경험이 없었다면 평소 타인을 배려하기 위해 어떠한 노력을 하는지, 그 노력이 어떤 결과를 가져왔는지 작성해주세요.",
    "essay_type": "설명글",
    "essay_level": "2",
    "essay_len": 716,
    "essay_main_subject": "타인을 중시하지 않았던 사례"
  }
}