{
  "paragraph": [
    {
      "paragraph_txt": "평소 좋은 습관을 기르기 위해 노력한 경험은 학교, 학원 숙제를 자기 전에 꼭 하고 자는것 입니다.#@문장구분# 예전에는 늦게 자도 숙제도 안하고 핸드폰만 했었는데 그 버릇을 고치기 위해 늦게 자더라도 그 날 숙제 분량은 다 하고 잔 결과는 학교, 학원에서 급하게 하지 않고 마음이 편안하다.#@문장구분# 두번재는 핸드폰 사용시간 줄이기 입니다.#@문장구분# 핸드폰과 티비 사용 때문에 시력이 많이 안좋아져서 핸드폰을 사용할 수 있는 시간을 정해 놓고 그 시간이 지나면 핸드폰을 사용할 수 없게 한 결과 안과에서 검진을 할때마다 그 시력을 유지하고 있다.#@문장구분# 핸드폰 사용시간을 줄이고 일주일 동안은 너무 심심하고 적응도 잘 안됬었는데 시간을 잘 나눠서 사용하다 보니까 나에겐 아직 부족한 시간 이지만 시간을 효율적으로 사용하다 보니까 예전보다는 훨씬 나아졌다고 생각한다.#@문장구분# 이 글을 쓰고 느낀점은 지금까지 고친 습관들을 보니까 뿌듯하기도 하고 앞으로도 내 단점을 찾으면 그 단점을 장점으로 고치기 위해 노력할것 이고 부족한 부분이 있으면 부족한 부분을 습관으로 길러보고 싶다.#@문장구분#",
      "paragraph_len": 642,
      "paragraph_id": "001"
    }
  ],
  "score": {
    "paragraph_score": [
      {
        "paragraph_scoreT": [
          3,
          3,
          2
        ],
        "paragraph_scoreT_detail": {
          "paragraph_scoreT_exp": [
            [
              3,
              3,
              0
            ],
            [
              3,
              3,
              0
            ],
            [
              2,
              2,
              0
            ]
          ]
        },
        "paragraph_scoreT_avg": 2.6666667,
        "paragraph_id": "001"
      }
    ],
    "essay_scoreT": [
      28.15,
      27.35,
      22.1
    ],
    "essay_scoreT_avg": 25.866667,
    "essay_scoreT_detail": {
      "essay_scoreT_org": [
        [
          3,
          3,
          3,
          2
        ],
        [
          3,
          3,
          3,
          2
        ],
        [
          2,
          2,
          3,
          3
        ]
      ],
      "essay_scoreT_cont": [
        [
          3,
          2,
          0,
          3
        ],
        [
          3,
          2,
          0,
          2
        ],
        [
          2,
          3,
          0,
          2
        ]
      ],
      "essay_scoreT_exp": [
        [
          3,
          3,
          0
        ],
        [
          3,
          3,
          0
        ],
        [
          2,
          2,
          0
        ]
      ]
    }
  },
  "student": {
    "date": "2021.07.19",
    "student_educated": true,
    "student_grade": "중등_1학년",
    "location": "041",
    "student_grade_group": "중등",
    "student_reading": 1
  },
  "rubric": {
    "essay_grade": "중등_1학년",
    "organization_weight": {
      "org_paragraph": 1,
      "org": 2,
      "org_essay": 5,
      "org_coherence": 1,
      "org_quantity": 1
    },
    "essay_type": "설명글",
    "content_weight": {
      "con_clearance": 4,
      "con_novelty": 4,
      "con": 4,
      "con_prompt": 0,
      "con_description": 2
    },
    "essay_main_subject": "습관들이기 위한 노력과 경험",
    "expression_weight": {
      "exp_style": 0,
      "exp_grammar": 3,
      "exp_vocab": 3,
      "exp": 4
    }
  },
  "correction": [],
  "info": {
    "essay_id": "ESSAY_33907",
    "essay_prompt": " 일상적으로 반복되는 행위를 습관이라고 정의합니다.\n\n 습관은 후천적인 행동 양식으로 특정한 행동 및 생각 등을 반복적으로 수행하게 되어 다음에 동일한 상황을 겪을 경우 이전에 행동했던 방식 그대로 행동하는 것을 의미합니다.\n\n 하지만 습관은 항상 좋은 것만은 아닙니다. 때론 나쁜 습관이 이미 익숙해져 있고 이를 바로잡기 위해 큰 노력을 해야 합니다.\n\n 이처럼 습관을 고치기 위한 노력 혹은 새로운 좋은 습관을 들이기 위해 했던 노력 및 경험에 대해 자유롭게 서술해 주세요. 좋은 습관을 들이기 위한 본인만의 노하우를 알려주셔도 좋습니다.",
    "essay_type": "설명글",
    "essay_level": "3",
    "essay_len": 522,
    "essay_main_subject": "습관들이기 위한 노력과 경험"
  }
}