{
  "paragraph": [
    {
      "paragraph_txt": "저는 예절에대한 기준에 이러케 생각합니다.#@문장구분#\n첫째:#@문장구분#버스에서 어른들께 자리를 양보하는것.#@문장구분#\n둘째:#@문장구분#어른들께 높임말을 사용하는것.#@문장구분#\n셋째:#@문장구분#가족끼리 싸우지 않는것.#@문장구분#\n넷째:#@문장구분# 사람들에게 배려 하는것.#@문장구분#\n다섯째:#@문장구분#친구들과 친하게 지내는것.#@문장구분#\n여섯째:#@문장구분#가족끼리 사이좋게 지내는것.#@문장구분#\n일곱째:#@문장구분#부모님 말씀 잘듣는것.#@문장구분#\n여덟째:#@문장구분#어르신을 공경하는것.#@문장구분#\n아홉째:#@문장구분#친구들과 즐겁게 생활하는것.#@문장구분#\n열째:#@문장구분#어른들을 배려하는것.#@문장구분#\n열한번째:#@문장구분#쓰레기를 줍는것.#@문장구분#\n열두번째:#@문장구분#어려운사람들께 기부하는것.#@문장구분#\n열세번째:#@문장구분#아픈친구 도와주는것.#@문장구분#\n열다섯번째:#@문장구분#부모님일 도와드리는것.#@문장구분#\n저는 이런일이 예절이라고 생각합니다.#@문장구분#",
      "paragraph_len": 901,
      "paragraph_id": "001"
    }
  ],
  "score": {
    "paragraph_score": [
      {
        "paragraph_scoreT": [
          2,
          1.5714285,
          1.5714285
        ],
        "paragraph_scoreT_detail": {
          "paragraph_scoreT_exp": [
            [
              2,
              2,
              0
            ],
            [
              2,
              1,
              0
            ],
            [
              2,
              1,
              0
            ]
          ]
        },
        "paragraph_scoreT_avg": 1.7142857,
        "paragraph_id": "001"
      }
    ],
    "essay_scoreT": [
      16.733334,
      14.5523815,
      14.5523815
    ],
    "essay_scoreT_avg": 15.279366,
    "essay_scoreT_detail": {
      "essay_scoreT_org": [
        [
          1,
          0,
          0,
          2
        ],
        [
          1,
          0,
          0,
          3
        ],
        [
          1,
          0,
          0,
          3
        ]
      ],
      "essay_scoreT_cont": [
        [
          2,
          1,
          0,
          2
        ],
        [
          2,
          1,
          0,
          1
        ],
        [
          2,
          1,
          0,
          1
        ]
      ],
      "essay_scoreT_exp": [
        [
          2,
          2,
          0
        ],
        [
          2,
          1,
          0
        ],
        [
          2,
          1,
          0
        ]
      ]
    }
  },
  "student": {
    "date": "2021.11.03",
    "student_educated": true,
    "student_grade": "초등_4학년",
    "location": "042",
    "student_grade_group": "초등",
    "student_reading": 3
  },
  "rubric": {
    "essay_grade": "초등_4학년",
    "organization_weight": {
      "org_paragraph": 0,
      "org": 2,
      "org_essay": 5,
      "org_coherence": 0,
      "org_quantity": 1
    },
    "essay_type": "설명글",
    "content_weight": {
      "con_clearance": 4,
      "con_novelty": 4,
      "con": 4,
      "con_prompt": 0,
      "con_description": 2
    },
    "essay_main_subject": "예절의 기준에 대한 의견",
    "expression_weight": {
      "exp_style": 0,
      "exp_grammar": 4,
      "exp_vocab": 3,
      "exp": 4
    }
  },
  "correction": [
    {
      "sentence_corr_txt_grammar": "저는 예절에 대한 기준에 이렇게 생각합니다.",
      "sentence_corr_reason": [
        ""
      ],
      "sentence_id": "0001",
      "sentence_corr_type": [
        "문법"
      ],
      "sentence_corr_detail_type": [
        "맞춤법"
      ],
      "sentence_txt": "저는 예절에대한 기준에 <문법_맞춤법>이러케 </문법_맞춤법>생각합니다.",
      "sentence_corr_txt_styling": "",
      "paragraph_id": "001"
    },
    {
      "sentence_corr_txt_grammar": "버스에서 어른들께 자리를 양보하는 것.",
      "sentence_corr_reason": [
        "띄어쓰기"
      ],
      "sentence_id": "0003",
      "sentence_corr_type": [
        "문법"
      ],
      "sentence_corr_detail_type": [
        "맞춤법"
      ],
      "sentence_txt": "버스에서 어른들께 자리를 <문법_맞춤법>양보하는것</문법_맞춤법>.",
      "sentence_corr_txt_styling": "",
      "paragraph_id": "001"
    },
    {
      "sentence_corr_txt_grammar": "어른들께 높임말을 사용하는 것.",
      "sentence_corr_reason": [
        "띄어쓰기"
      ],
      "sentence_id": "0005",
      "sentence_corr_type": [
        "문법"
      ],
      "sentence_corr_detail_type": [
        "맞춤법"
      ],
      "sentence_txt": "어른들께 높임말을 <문법_맞춤법>사용하는것</문법_맞춤법>.",
      "sentence_corr_txt_styling": "",
      "paragraph_id": "001"
    },
    {
      "sentence_corr_txt_grammar": "가족끼리 싸우지 않는 것.",
      "sentence_corr_reason": [
        "띄어쓰기"
      ],
      "sentence_id": "0007",
      "sentence_corr_type": [
        "문법"
      ],
      "sentence_corr_detail_type": [
        "맞춤법"
      ],
      "sentence_txt": "가족끼리 싸우지 <문법_맞춤법>않는것</문법_맞춤법>.",
      "sentence_corr_txt_styling": "",
      "paragraph_id": "001"
    },
    {
      "sentence_corr_txt_grammar": " 사람들에게 배려 하는 것.",
      "sentence_corr_reason": [
        "띄어쓰기"
      ],
      "sentence_id": "0009",
      "sentence_corr_type": [
        "문법"
      ],
      "sentence_corr_detail_type": [
        "맞춤법"
      ],
      "sentence_txt": " 사람들에게 배려 <문법_맞춤법>하는것</문법_맞춤법>.",
      "sentence_corr_txt_styling": "",
      "paragraph_id": "001"
    },
    {
      "sentence_corr_txt_grammar": "친구들과 친하게 지내는 것.",
      "sentence_corr_reason": [
        "띄어쓰기"
      ],
      "sentence_id": "0011",
      "sentence_corr_type": [
        "문법"
      ],
      "sentence_corr_detail_type": [
        "맞춤법"
      ],
      "sentence_txt": "친구들과 친하게 <문법_맞춤법>지내는것</문법_맞춤법>.",
      "sentence_corr_txt_styling": "",
      "paragraph_id": "001"
    },
    {
      "sentence_corr_txt_grammar": "가족끼리 사이좋게 지내는 것.",
      "sentence_corr_reason": [
        "띄어쓰기"
      ],
      "sentence_id": "0013",
      "sentence_corr_type": [
        "문법"
      ],
      "sentence_corr_detail_type": [
        "맞춤법"
      ],
      "sentence_txt": "가족끼리 사이좋게 <문법_맞춤법>지내는것</문법_맞춤법>.",
      "sentence_corr_txt_styling": "",
      "paragraph_id": "001"
    },
    {
      "sentence_corr_txt_grammar": "부모님 말씀 잘 듣는 것.",
      "sentence_corr_reason": [
        "띄어쓰기"
      ],
      "sentence_id": "0015",
      "sentence_corr_type": [
        "문법"
      ],
      "sentence_corr_detail_type": [
        "맞춤법"
      ],
      "sentence_txt": "부모님 말씀 <문법_맞춤법>잘듣는것</문법_맞춤법>.",
      "sentence_corr_txt_styling": "",
      "paragraph_id": "001"
    },
    {
      "sentence_corr_txt_grammar": "어르신을 공경하는 것.",
      "sentence_corr_reason": [
        "띄어쓰기"
      ],
      "sentence_id": "0017",
      "sentence_corr_type": [
        "문법"
      ],
      "sentence_corr_detail_type": [
        "맞춤법"
      ],
      "sentence_txt": "어르신을 <문법_맞춤법>공경하는것</문법_맞춤법>.",
      "sentence_corr_txt_styling": "",
      "paragraph_id": "001"
    },
    {
      "sentence_corr_txt_grammar": "친구들과 즐겁게 생활하는 것.",
      "sentence_corr_reason": [
        "띄어쓰기"
      ],
      "sentence_id": "0019",
      "sentence_corr_type": [
        "문법"
      ],
      "sentence_corr_detail_type": [
        "맞춤법"
      ],
      "sentence_txt": "친구들과 즐겁게 <문법_맞춤법>생활하는것</문법_맞춤법>.",
      "sentence_corr_txt_styling": "",
      "paragraph_id": "001"
    },
    {
      "sentence_corr_txt_grammar": "어른들을 배려하는 것.",
      "sentence_corr_reason": [
        "띄어쓰기"
      ],
      "sentence_id": "0021",
      "sentence_corr_type": [
        "문법"
      ],
      "sentence_corr_detail_type": [
        "맞춤법"
      ],
      "sentence_txt": "어른들을 <문법_맞춤법>배려하는것</문법_맞춤법>.",
      "sentence_corr_txt_styling": "",
      "paragraph_id": "001"
    },
    {
      "sentence_corr_txt_grammar": "\n열한 번째:",
      "sentence_corr_reason": [
        "띄어쓰기",
        ""
      ],
      "sentence_id": "0022",
      "sentence_corr_type": [
        "문법",
        "스타일링"
      ],
      "sentence_corr_detail_type": [
        "맞춤법",
        "패러프레이징"
      ],
      "sentence_txt": "\n<문법_맞춤법>열한번째</문법_맞춤법>:",
      "sentence_corr_txt_styling": "\n열한 번째:",
      "paragraph_id": "001"
    },
    {
      "sentence_corr_txt_grammar": "쓰레기를 줍는 것.",
      "sentence_corr_reason": [
        "띄어쓰기"
      ],
      "sentence_id": "0023",
      "sentence_corr_type": [
        "문법"
      ],
      "sentence_corr_detail_type": [
        "맞춤법"
      ],
      "sentence_txt": "쓰레기를 <문법_맞춤법>줍는것</문법_맞춤법>.",
      "sentence_corr_txt_styling": "",
      "paragraph_id": "001"
    },
    {
      "sentence_corr_txt_grammar": "\n열두 번째:",
      "sentence_corr_reason": [
        "띄어쓰기",
        ""
      ],
      "sentence_id": "0024",
      "sentence_corr_type": [
        "문법",
        "스타일링"
      ],
      "sentence_corr_detail_type": [
        "맞춤법",
        "패러프레이징"
      ],
      "sentence_txt": "\n<문법_맞춤법>열두번째</문법_맞춤법>:",
      "sentence_corr_txt_styling": "\n열두 번째:",
      "paragraph_id": "001"
    },
    {
      "sentence_corr_txt_grammar": "어려운 사람들께 기부하는 것.",
      "sentence_corr_reason": [
        "띄어쓰기"
      ],
      "sentence_id": "0025",
      "sentence_corr_type": [
        "문법"
      ],
      "sentence_corr_detail_type": [
        "맞춤법"
      ],
      "sentence_txt": "<문법_맞춤법>어려운사람들께 </문법_맞춤법>기부하는것.",
      "sentence_corr_txt_styling": "",
      "paragraph_id": "001"
    },
    {
      "sentence_corr_txt_grammar": "\n열세 번째:",
      "sentence_corr_reason": [
        "띄어쓰기",
        ""
      ],
      "sentence_id": "0026",
      "sentence_corr_type": [
        "문법",
        "스타일링"
      ],
      "sentence_corr_detail_type": [
        "맞춤법",
        "패러프레이징"
      ],
      "sentence_txt": "\n<문법_맞춤법>열세번째</문법_맞춤법>:",
      "sentence_corr_txt_styling": "\n열세 번째:",
      "paragraph_id": "001"
    },
    {
      "sentence_corr_txt_grammar": "아픈 친구 도와주는 것.",
      "sentence_corr_reason": [
        "띄어쓰기"
      ],
      "sentence_id": "0027",
      "sentence_corr_type": [
        "문법"
      ],
      "sentence_corr_detail_type": [
        "맞춤법"
      ],
      "sentence_txt": "<문법_맞춤법>아픈친구 </문법_맞춤법>도와주는것.",
      "sentence_corr_txt_styling": "",
      "paragraph_id": "001"
    },
    {
      "sentence_corr_txt_grammar": "\n열다섯 번째:",
      "sentence_corr_reason": [
        "띄어쓰기",
        ""
      ],
      "sentence_id": "0028",
      "sentence_corr_type": [
        "문법",
        "스타일링"
      ],
      "sentence_corr_detail_type": [
        "맞춤법",
        "패러프레이징"
      ],
      "sentence_txt": "\n<문법_맞춤법>열다섯번째</문법_맞춤법>:",
      "sentence_corr_txt_styling": "\n열다섯 번째:",
      "paragraph_id": "001"
    },
    {
      "sentence_corr_txt_grammar": "부모님 일 도와드리는 것.",
      "sentence_corr_reason": [
        "띄어쓰기"
      ],
      "sentence_id": "0029",
      "sentence_corr_type": [
        "문법"
      ],
      "sentence_corr_detail_type": [
        "맞춤법"
      ],
      "sentence_txt": "<문법_맞춤법>부모님일 </문법_맞춤법>도와드리는것.",
      "sentence_corr_txt_styling": "",
      "paragraph_id": "001"
    },
    {
      "sentence_corr_txt_grammar": "\n저는 이런 일이 예절이라고 생각합니다.",
      "sentence_corr_reason": [
        "띄어쓰기"
      ],
      "sentence_id": "0030",
      "sentence_corr_type": [
        "문법"
      ],
      "sentence_corr_detail_type": [
        "맞춤법"
      ],
      "sentence_txt": "\n저는 <문법_맞춤법>이런일이</문법_맞춤법> 예절이라고 생각합니다.",
      "sentence_corr_txt_styling": "",
      "paragraph_id": "001"
    }
  ],
  "info": {
    "essay_id": "ESSAY_47206",
    "essay_prompt": " 여러분은 버스 안에서 노약자분께 자리를 양보한 적이 있나요? 가정에서 부모님 말씀을 잘 듣고 형제들과 사이좋게 지내고 있나요? 학교에서 친구들과 배려하며 즐겁게 생활하나요?\n\n 가족을 사랑하고, 친구들과 친하게 지내고, 어르신을 공경하는 등 우리는 다른 사람을 존중하고 때와 장소에 알맞은 예절을 지키기 위해 교육을 받고 있습니다.\n\n 다만, 사람마다 예절의 기준은 다를 수 있다고 생각해본 적 있으신가요?\n\n 친한 사람들에게만 예절을 지키면 된다고 생각하는 사람도 있고 모든 사람이 평등하게 예절을 지켜야 한다고 생각하는 사람이 있어요. 또한, 아이들에게는 반말해도 된다는 사람들도 있고 아이들에게도 존댓말을 하며 존중해야 한다는 사람들도 있습니다.\n\n 여러분이 생각하는 예절의 기준은 무엇인가요? 그렇게 생각한 이유는 무엇인지 작성해보세요.",
    "essay_type": "설명글",
    "essay_level": "3",
    "essay_len": 302,
    "essay_main_subject": "예절의 기준에 대한 의견"
  }
}