{
  "paragraph": [
    {
      "paragraph_txt": "나도 겪어본 학교 폭력#@문장구분#\n 혹시 학교폭력을 당해 보셨습니까?#@문장구분#\n요즘 학교폭력이 빈번하게 일어납니다.#@문장구분# 우리가 열심히 막는다 해도 학교폭력은 멈추지 않습니다.#@문장구분# 어떻게 해아 학교폭력을 줄일 수 있을까요?#@문장구분#학교 폭력에 대한 처벌을 강화합니다.#@문장구분#\n 첫째, 학교 폭력은 계속 이어질 수 있는데 한번 처벌을 겪고 나오면 계속 이어질 가능성이 낮아집니다.#@문장구분# 처벌이 강화되면 가해자는 심한 처벌을 받게 되고, 이러한 조치는 학교 폭력 예방에도 일부 효과가 있기 때문에 \"일석이조\" 입니다.#@문장구분# 그리고 현재는 엄벌주의적 폭력은 금지여서 '장난'이라는 방어막 뒤에 숨어 학교 폭력을 이어갈수도 있습니다.#@문장구분# 아니면 그 처벌이 무섭지 않아 그냥 이러가는 사례도 있습니다.#@문장구분#실제로 주인공이 학교 폭력 피해자를 도와 가해자를 신고했지만 가해자는 사과만 하고 타겟이 자기로 바뀌어 협박을 받았습니다.#@문장구분#\n 둘째, 선량한 학생들에게 안도감을 줍니다.#@문장구분# 만약 자신의 반에 학교 폭력의 주요 원인인 무리가 있다면 '나도 학교 폭력을 당하면 어쩌지?' 라는 생각 때문에 마음이 불안할 것입니다.#@문장구분# 'Science on'의 논문에 따르면 연령이 다양한 학생 때 학교 폭력을 경험한 사람들을 대상으로 실험을 진행했습니다.#@문장구분# 그랬더니 학교 폭력 피해자의 심리는 두렵고 불안함, 팽창한 무력감과 막막함, 절망함에 뒤덮인 불안감, 망각하고 싶은 현실 등이었습니다.#@문장구분# 그리고 성인이 된 후 심리적 현상은 고통과 절망의 늪, 해체된 삶의 고통, 중독 증상 발현 등이 있습니다.#@문장구분# 후유증은 관계심의 문제, 특히 사회적 부적응을 동반합니다.#@문장구분# 그럼 그때의 고통과 기억이 매우 선명하고 구체적이게 되고 그걸 잊기 위한 다양한 중독 현상, 중독 증상의 심화, 자살, 살해 충동, 심각한 병리상태로 치료를 안 받으면 안되는 상황까지 일어나게 됩니다.#@문장구분# 저도 마찬가지로 은따를 당한적이 있었는데, 방과 후에 언니들이 있으면 심장이 엄청나게 뛰고, 정신이 아찔했습니다.#@문장구분#\n 하지만 처벌이 강화된다면 이런 심리적 불안감이 완화될 것입니다.#@문장구분# \n 이처럼 심각한 문제를 일으키는 학교폭력,이제는 줄여야 합니다.#@문장구분#그러므로 학교 폭력 처벌을 강화해야 합니다",
      "paragraph_len": 1455,
      "paragraph_id": "001"
    }
  ],
  "score": {
    "paragraph_score": [
      {
        "paragraph_scoreT": [
          3,
          3,
          3
        ],
        "paragraph_scoreT_detail": {
          "paragraph_scoreT_exp": [
            [
              3,
              3,
              0
            ],
            [
              3,
              3,
              0
            ],
            [
              3,
              3,
              0
            ]
          ]
        },
        "paragraph_scoreT_avg": 3,
        "paragraph_id": "001"
      }
    ],
    "essay_scoreT": [
      30,
      27.777779,
      30
    ],
    "essay_scoreT_avg": 29.25926,
    "essay_scoreT_detail": {
      "essay_scoreT_org": [
        [
          3,
          0,
          3,
          3
        ],
        [
          3,
          0,
          3,
          3
        ],
        [
          3,
          0,
          3,
          3
        ]
      ],
      "essay_scoreT_cont": [
        [
          3,
          3,
          3,
          3
        ],
        [
          3,
          1,
          2,
          3
        ],
        [
          3,
          3,
          3,
          3
        ]
      ],
      "essay_scoreT_exp": [
        [
          3,
          3,
          0
        ],
        [
          3,
          3,
          0
        ],
        [
          3,
          3,
          0
        ]
      ]
    }
  },
  "student": {
    "date": "2021.10.19",
    "student_educated": true,
    "student_grade": "초등_6학년",
    "location": "042",
    "student_grade_group": "초등",
    "student_reading": 2
  },
  "rubric": {
    "essay_grade": "초등_6학년",
    "organization_weight": {
      "org_paragraph": 0,
      "org": 3,
      "org_essay": 7,
      "org_coherence": 2,
      "org_quantity": 1
    },
    "essay_type": "주장",
    "content_weight": {
      "con_clearance": 4,
      "con_novelty": 2,
      "con": 4,
      "con_prompt": 1,
      "con_description": 2
    },
    "essay_main_subject": "폭력 예방 방법",
    "expression_weight": {
      "exp_style": 0,
      "exp_grammar": 3,
      "exp_vocab": 3,
      "exp": 3
    }
  },
  "correction": [],
  "info": {
    "essay_id": "ESSAY_53250",
    "essay_prompt": " 요즘 학교에서는 신체적인 폭력뿐만 아니라 미디어 발달로 인한 사이버 폭력과 언어폭력이 점점 많아지고 있습니다.\n\n 또한, 학교폭력 피해를 본 학생의 나이가 점점 낮아지고 있어 심각한 사회적 문제로 나타나고 있습니다.\n\n 학교폭력을 예방하기 위해 노력을 많이 하고 있지만 제대로 해결되지 않는다는 의견이 많습니다.\n\n 한쪽에서는 학교폭력을 일으킨 학생에 대한 처벌을 더욱 강력하게 하자는 의견이 있습니다. 더 나아가 폭력에 한에서는 법을 개편해서 청소년 보호법이 아닌 강력한 법을 시행하자는 의견도 있습니다.\n\n 다른 쪽에서는 학생에 대한 처벌보다 보호자에 대한 처벌을 강화하는 의견을 제시하기도 합니다.\n\n 학교 폭력을 예방하는 방법과 대처하는 방법은 다양합니다. 학교 폭력을 줄일 수 있는 방법에 대한 자기 생각을 작성해주세요. 그리고 그 이유에 관해 설명해주세요.",
    "essay_type": "주장",
    "essay_level": "2",
    "essay_len": 1037,
    "essay_main_subject": "폭력 예방 방법"
  }
}